.DS_Store
intelcom_helper/__init__.py
intelcom_helper/snowflake.py
intelcom_helper-0.5.0.dist-info/METADATA
intelcom_helper-0.5.0.dist-info/WHEEL
intelcom_helper-0.5.0.dist-info/top_level.txt
intelcom_helper-0.5.0.dist-info/RECORD
