Metadata-Version: 2.1
Name: intelcom-helper
Version: 0.5.0
Summary: Code used frequently at Intelcom
Home-page: UNKNOWN
Author: Simon Prudhomme
Author-email: sphomme@intelcomexpress.com
License: UNKNOWN
Platform: UNKNOWN
Classifier: Programming Language :: Python :: 3
Classifier: License :: OSI Approved :: MIT License
Requires-Dist: pandas
Requires-Dist: snowflake-connector-python[pandas]
Requires-Dist: snowflake-sqlalchemy
Requires-Dist: sqlalchemy
